LICENSE
MANIFEST.in
README.md
setup.py
granite/__init__.py
granite/environment.py
granite/exceptions.py
granite/io.py
granite/sphinx.py
granite/testcase.py
granite/utils.py
granite.egg-info/PKG-INFO
granite.egg-info/SOURCES.txt
granite.egg-info/dependency_links.txt
granite.egg-info/requires.txt
granite.egg-info/top_level.txt
granite.egg-info/zip-safe