Metadata-Version: 2.1
Name: granite
Version: 0.0.5
Summary: Augments the unittest TestCase API by providing additional utilities useful for Python tools.
Home-page: https://github.com/frenchtoast747/granite
Author: Aaron Boman
Author-email: aaron@aaronboman.com
License: MIT
Platform: UNKNOWN
Classifier: Programming Language :: Python :: 2
Classifier: Programming Language :: Python :: 3
Classifier: License :: OSI Approved :: MIT License
Classifier: Operating System :: OS Independent
Classifier: Topic :: Software Development :: Testing
Classifier: Topic :: Software Development :: Testing :: Unit
Classifier: Topic :: Utilities
